progress_timer/__init__.py
progress_timer/progress_timer.py
progress_timer-0.2.0.dist-info/LICENSE
progress_timer-0.2.0.dist-info/METADATA
progress_timer-0.2.0.dist-info/WHEEL
progress_timer-0.2.0.dist-info/top_level.txt
progress_timer-0.2.0.dist-info/RECORD
